README.md
setup.cfg
setup.py
distributionuploadtest/Binomialdistribution.py
distributionuploadtest/Gaussiandistribution.py
distributionuploadtest/Generaldistribution.py
distributionuploadtest/__init__.py
distributionuploadtest.egg-info/PKG-INFO
distributionuploadtest.egg-info/SOURCES.txt
distributionuploadtest.egg-info/dependency_links.txt
distributionuploadtest.egg-info/not-zip-safe
distributionuploadtest.egg-info/top_level.txt